pyrepo_mcda/__init__.py
pyrepo_mcda/additions.py
pyrepo_mcda/compromise_rankings.py
pyrepo_mcda/correlations.py
pyrepo_mcda/distance_metrics.py
pyrepo_mcda/normalizations.py
pyrepo_mcda/sensitivity_analysis_weights_percentages.py
pyrepo_mcda/sensitivity_analysis_weights_values.py
pyrepo_mcda/weighting_methods.py
pyrepo_mcda/mcda_methods/__init__.py
pyrepo_mcda/mcda_methods/ahp.py
pyrepo_mcda/mcda_methods/aras.py
pyrepo_mcda/mcda_methods/cocoso.py
pyrepo_mcda/mcda_methods/codas.py
pyrepo_mcda/mcda_methods/copras.py
pyrepo_mcda/mcda_methods/cradis.py
pyrepo_mcda/mcda_methods/edas.py
pyrepo_mcda/mcda_methods/mabac.py
pyrepo_mcda/mcda_methods/marcos.py
pyrepo_mcda/mcda_methods/mcda_method.py
pyrepo_mcda/mcda_methods/multimoora.py
pyrepo_mcda/mcda_methods/promethee.py
pyrepo_mcda/mcda_methods/prosa_c.py
pyrepo_mcda/mcda_methods/pvm.py
pyrepo_mcda/mcda_methods/saw.py
pyrepo_mcda/mcda_methods/spotis.py
pyrepo_mcda/mcda_methods/topsis.py
pyrepo_mcda/mcda_methods/vikor.py
pyrepo_mcda/mcda_methods/vikor_smaa.py
pyrepo_mcda/mcda_methods/vmcm.py
pyrepo_mcda/mcda_methods/waspas.py
pyrepo_mcda-0.1.8.dist-info/LICENSE
pyrepo_mcda-0.1.8.dist-info/METADATA
pyrepo_mcda-0.1.8.dist-info/WHEEL
pyrepo_mcda-0.1.8.dist-info/top_level.txt
pyrepo_mcda-0.1.8.dist-info/RECORD
