Metadata-Version: 2.1
Name: pyrepo-mcda
Version: 0.1.8
Summary: Python library for Multi-Criteria Decision Analysis.
Home-page: https://github.com/energyinpython/pyrepo-mcda
Author: Aleksandra Bączkiewicz
Author-email: aleksandra.baczkiewicz@phd.usz.edu.pl
Classifier: Programming Language :: Python :: 3
Classifier: License :: OSI Approved :: MIT License
Classifier: Operating System :: OS Independent
Requires-Python: >=3.6
License-File: LICENSE
Requires-Dist: numpy
Requires-Dist: pandas
Requires-Dist: scipy
